cfcli/__init__.py
cfcli/main.py
cfcli/commands/__init__.py
cfcli/commands/contests.py
cfcli/commands/help.py
cfcli/commands/log.py
cfcli/commands/problemset.py
cfcli/commands/rating.py
cfcli/commands/streak.py
cfcli/commands/user.py
cfcli_py_tool-1.0.2.dist-info/METADATA
cfcli_py_tool-1.0.2.dist-info/WHEEL
cfcli_py_tool-1.0.2.dist-info/entry_points.txt
cfcli_py_tool-1.0.2.dist-info/top_level.txt
cfcli_py_tool-1.0.2.dist-info/RECORD
