Metadata-Version: 2.4
Name: cfcli-py-tool
Version: 1.0.2
Summary: A CLI tool for interacting with the Codeforces API
Author-email: Kashyap Sukshavasi <ksukshavasi@gmail.com>
Requires-Python: >=3.8
Requires-Dist: rich
Requires-Dist: InquirerPy
Requires-Dist: requests
Requires-Dist: matplotlib
